msreport/__init__.py
msreport/analyze.py
msreport/errors.py
msreport/export.py
msreport/fasta.py
msreport/impute.py
msreport/isobar.py
msreport/normalize.py
msreport/peptidoform.py
msreport/qtable.py
msreport/reader.py
msreport/aggregate/__init__.py
msreport/aggregate/condense.py
msreport/aggregate/pivot.py
msreport/aggregate/summarize.py
msreport/helper/__init__.py
msreport/helper/calc.py
msreport/helper/maxlfq.py
msreport/helper/table.py
msreport/helper/temp.py
msreport/plot/__init__.py
msreport/plot/_partial_plots.py
msreport/plot/comparison.py
msreport/plot/distribution.py
msreport/plot/multivariate.py
msreport/plot/quality.py
msreport/plot/style.py
msreport/plot/style_sheets/msreport-notebook.mplstyle
msreport/plot/style_sheets/seaborn-whitegrid.mplstyle
msreport/rinterface/__init__.py
msreport/rinterface/limma.py
msreport/rinterface/rinstaller.py
msreport/rinterface/rscripts/limma.R
msreport-0.0.31.dist-info/licenses/LICENSE.txt
msreport-0.0.31.dist-info/METADATA
msreport-0.0.31.dist-info/WHEEL
msreport-0.0.31.dist-info/top_level.txt
msreport-0.0.31.dist-info/RECORD
