Metadata-Version: 2.4
Name: msreport
Version: 0.0.31
Summary: Post processing and analysis of quantitative proteomics data
Author-email: "David M. Hollenstein" <hollenstein.david@gmail.com>
License-Expression: Apache-2.0
Project-URL: homepage, https://github.com/hollenstein/msreport
Project-URL: documentation, https://hollenstein.github.io/msreport/
Project-URL: changelog, https://github.com/hollenstein/msreport/blob/main/CHANGELOG.md
Keywords: mass spectrometry,proteomics,post processing,data analysis
Classifier: Development Status :: 4 - Beta
Classifier: Programming Language :: Python :: 3.10
Classifier: Programming Language :: Python :: 3.11
Classifier: Programming Language :: Python :: 3.12
Classifier: Programming Language :: Python :: 3.13
Classifier: Topic :: Scientific/Engineering :: Bio-Informatics
Requires-Python: >=3.10
License-File: LICENSE.txt
Requires-Dist: adjustText<1.0.0,>=0.7.0
Requires-Dist: matplotlib>=3.5.2
Requires-Dist: numpy>=1.21.5
Requires-Dist: pandas>=1.4.4
Requires-Dist: profasta>=0.0.4
Requires-Dist: pyteomics>=4.6.0
Requires-Dist: pyyaml>=6.0.0
Requires-Dist: scikit-learn>=1.0.0
Requires-Dist: scipy>=1.9.1
Requires-Dist: seaborn>=0.12.0
Requires-Dist: statsmodels>=0.13.2
Requires-Dist: typing_extensions>=4
Provides-Extra: r
Requires-Dist: rpy2<3.5.13,>=3.5.3; extra == "r"
Provides-Extra: dev
Requires-Dist: mypy>=1.15.0; extra == "dev"
Requires-Dist: pytest>=8.3.5; extra == "dev"
Provides-Extra: docs
Requires-Dist: mkdocs-awesome-nav>=3.1.2; extra == "docs"
Requires-Dist: mkdocs-macros-plugin>=1.3.7; extra == "docs"
Requires-Dist: mkdocs-material>=9.6.15; extra == "docs"
Requires-Dist: mkdocs-roamlinks-plugin>=0.3.2; extra == "docs"
Requires-Dist: mkdocstrings-python>=1.16.12; extra == "docs"
Requires-Dist: ruff>=0.12.2; extra == "docs"
Provides-Extra: test
Requires-Dist: pytest>=8.3.5; extra == "test"
Dynamic: license-file
